{"ast":null,"code":"import isArrayLike from './_isArrayLike.js';\nimport keys from './keys.js';\nimport optimizeCb from './_optimizeCb.js'; // Internal helper to create a reducing function, iterating left or right.\n\nexport default function createReduce(dir) {\n  // Wrap code that reassigns argument variables in a separate function than\n  // the one that accesses `arguments.length` to avoid a perf hit. (#1991)\n  var reducer = function reducer(obj, iteratee, memo, initial) {\n    var _keys = !isArrayLike(obj) && keys(obj),\n        length = (_keys || obj).length,\n        index = dir > 0 ? 0 : length - 1;\n\n    if (!initial) {\n      memo = obj[_keys ? _keys[index] : index];\n      index += dir;\n    }\n\n    for (; index >= 0 && index < length; index += dir) {\n      var currentKey = _keys ? _keys[index] : index;\n      memo = iteratee(memo, obj[currentKey], currentKey, obj);\n    }\n\n    return memo;\n  };\n\n  return function (obj, iteratee, memo, context) {\n    var initial = arguments.length >= 3;\n    return reducer(obj, optimizeCb(iteratee, context, 4), memo, initial);\n  };\n}","map":null,"metadata":{},"sourceType":"module"}